isr_debian/__init__.py
isr_debian/control_files.py
isr_debian/io.py
isr_debian-0.2.data/scripts/isr_make_debian
isr_debian-0.2.dist-info/METADATA
isr_debian-0.2.dist-info/WHEEL
isr_debian-0.2.dist-info/top_level.txt
isr_debian-0.2.dist-info/zip-safe
isr_debian-0.2.dist-info/RECORD
